{
  "kind": "singleType",
  "collectionName": "shops",
  "info": {
    "singularName": "shop",
    "pluralName": "shops",
    "displayName": "Shop",
    "description": ""
  },
  "options": {
    "draftAndPublish": false
  },
  "pluginOptions": {
    "i18n": {
      "localized": true
    }
  },
  "attributes": {
    "filters": {
      "displayName": "filters",
      "type": "component",
      "repeatable": false,
      "pluginOptions": {
        "i18n": {
          "localized": true
        }
      },
      "component": "shoppage.filters"
    },
    "general": {
      "displayName": "general",
      "type": "component",
      "repeatable": false,
      "pluginOptions": {
        "i18n": {
          "localized": true
        }
      },
      "component": "shoppage.general",
      "required": true
    }
  }
}
